<?xml version="1.0" encoding="ISO-8859-1"?>

<items xmlns:xsi="http://www.w3.org/2001/XMLSchema-instance"
       xsi:noNamespaceSchemaLocation="items.xsd">

    <collectiontypes>
        <collectiontype code="ListOfStrings" elementtype="java.lang.String" type="list"/>
    </collectiontypes>

    <enumtypes>
        <enumtype code="NonDynamicEnum">
            <value code="value"/>
        </enumtype>

        <enumtype code="DynamicEnum" dynamic="true">
            <value code="value"/>
        </enumtype>
    </enumtypes>

    <maptypes>
        <maptype code="Map" argumenttype="java.lang.String" returntype="java.lang.Integer"/>
    </maptypes>

    <relations>
        <relation code="ItemAllTypesContainerRelation" localized="false">
            <sourceElement type="AllTypesContainer" qualifier="allTypesContainer" cardinality="one">
                <modifiers read="true" write="true" search="true" optional="true"/>
            </sourceElement>
            <targetElement type="Item3" qualifier="item3" cardinality="many">
                <modifiers read="true" write="true" search="true" optional="true"/>
            </targetElement>
        </relation>

        <relation code="One2many" localized="false">
            <sourceElement type="Item1" qualifier="item1" cardinality="one">
                <modifiers read="true" write="true" search="true" optional="false"/>
            </sourceElement>
            <targetElement type="Item2" qualifier="item2" cardinality="many">
                <modifiers read="true" write="true" search="true" optional="false"/>
            </targetElement>
        </relation>

        <relation code="Many2many" localized="false">
            <deployment table="item2item" typecode="11110"/>
            <sourceElement type="Item3" qualifier="items3" cardinality="many">
                <modifiers read="true" write="true" search="true" optional="false"/>
            </sourceElement>
            <targetElement type="Item4" qualifier="items4" cardinality="many">
                <modifiers read="true" write="true" search="true" optional="false"/>
            </targetElement>
        </relation>
    </relations>

    <itemtypes>
        <itemtype code="AllTypesContainer">
            <deployment table="allTypesContainer" typecode="11111"/>
            <attributes>
                <attribute qualifier="name" type="java.lang.String">
                    <modifiers read="true" write="true" search="true" unique="true"/>
                    <persistence type="property"/>
                </attribute>
                <attribute qualifier="nonDynamicEnum" type="NonDynamicEnum">
                    <modifiers read="true" write="true" search="true"/>
                    <persistence type="property"/>
                </attribute>
                <attribute qualifier="map" type="Map">
                    <modifiers read="true" write="true" search="true"/>
                    <persistence type="property"/>
                </attribute>
                <attribute qualifier="listOfStrings" type="ListOfStrings">
                    <modifiers read="true" write="true" search="true"/>
                    <persistence type="property"/>
                </attribute>
                <attribute qualifier="one2one" type="Item4">
                    <modifiers read="true" write="true" search="true"/>
                    <persistence type="property"/>
                </attribute>
                <attribute qualifier="many2many" type="Many2many">
                    <persistence type="property"/>
                </attribute>
            </attributes>
        </itemtype>

        <itemtype code="Item1">
            <deployment table="item1" typecode="11112"/>
            <attributes>
                <attribute qualifier="name" type="java.lang.String">
                    <modifiers read="true" write="true" search="true" unique="true"/>
                    <persistence type="property"/>
                </attribute>
                <attribute qualifier="item4" type="item4">
                    <modifiers read="true" write="true" search="true" unique="true"/>
                    <persistence type="property"/>
                </attribute>
            </attributes>
        </itemtype>

        <itemtype code="Item2">
            <deployment table="item2" typecode="11113"/>
            <attributes>
                <attribute qualifier="quantity" type="java.lang.Long">
                    <modifiers read="true" write="true" search="true"/>
                    <persistence type="property"/>
                </attribute>
            </attributes>
        </itemtype>

        <itemtype code="Item3">
            <deployment table="item3" typecode="11114"/>
            <attributes>
                <attribute qualifier="name" type="java.lang.String">
                    <modifiers read="true" write="true" search="true" unique="true"/>
                    <persistence type="property"/>
                </attribute>
            </attributes>
        </itemtype>

        <itemtype code="Item4">
            <deployment table="item4" typecode="11115"/>
            <attributes>
                <attribute qualifier="quantity" type="java.lang.Long">
                    <modifiers read="true" write="true" search="true"/>
                    <persistence type="property"/>
                </attribute>
            </attributes>
        </itemtype>
    </itemtypes>
</items>